example/__init__.py
example/app.py
sanic_devtools/__init__.py
sanic_devtools/cli.py
sanic_devtools/config.py
sanic_devtools/exceptions.py
sanic_devtools/log.py
sanic_devtools/main.py
sanic_devtools/runner.py
sanic_devtools/serve.py
sanic_devtools/version.py
sanic_devtools/watch.py
tests/__init__.py
tests/conftest.py
tests/test_cli.py
tests/test_config.py
tests/test_log.py
tests/test_main.py
tests/test_serve.py
tests/test_watch.py
sanic_devtools-0.1.0.dist-info/LICENSE
sanic_devtools-0.1.0.dist-info/LICENSE.md
sanic_devtools-0.1.0.dist-info/METADATA
sanic_devtools-0.1.0.dist-info/WHEEL
sanic_devtools-0.1.0.dist-info/entry_points.txt
sanic_devtools-0.1.0.dist-info/top_level.txt
sanic_devtools-0.1.0.dist-info/RECORD
