Metadata-Version: 2.1
Name: sanic-devtools
Version: 0.1.0
Summary: dev tools for Sanic
Home-page: https://github.com/yunstanford/sanic-devtools/
Author: Yun Xu
Author-email: yunxu1992@gmail.com
License: UNKNOWN
Platform: UNKNOWN
Classifier: Development Status :: 5 - Production/Stable
Classifier: Operating System :: MacOS
Classifier: Operating System :: POSIX :: Linux
Classifier: Topic :: System :: Software Distribution
Classifier: License :: OSI Approved :: MIT License
Classifier: Programming Language :: Python
Classifier: Programming Language :: Python :: 3
Classifier: Programming Language :: Python :: 3.5
Classifier: Programming Language :: Python :: 3.6
Classifier: Programming Language :: Python :: 3.7
Requires-Dist: aiohttp (>=3.5.0)
Requires-Dist: cookiecutter
Requires-Dist: click (>=6.6)
Requires-Dist: devtools (>=0.5)
Requires-Dist: Pygments (>=2.2.0)
Requires-Dist: watchgod (>=0.2)
Requires-Dist: sanic
